grafana_loki_client/__init__.py
grafana_loki_client/api/__init__.py
grafana_loki_client/api/query/__init__.py
grafana_loki_client/api/query/get_loki_api_v1_query.py
grafana_loki_client/api/query_range/__init__.py
grafana_loki_client/api/query_range/get_loki_api_v1_query_range.py
grafana_loki_client/client.py
grafana_loki_client/models/__init__.py
grafana_loki_client/models/direction.py
grafana_loki_client/models/query_response_body.py
grafana_loki_client/models/query_response_data.py
grafana_loki_client/models/query_response_data_result_type.py
grafana_loki_client/models/query_response_metric.py
grafana_loki_client/models/query_response_metric_level.py
grafana_loki_client/models/query_response_result.py
grafana_loki_client/models/query_response_streams.py
grafana_loki_client/models/query_statistics.py
grafana_loki_client/models/query_statistics_ingester.py
grafana_loki_client/models/query_statistics_querier.py
grafana_loki_client/models/query_statistics_store.py
grafana_loki_client/models/query_statistics_store_chunk.py
grafana_loki_client/models/query_statistics_summary.py
grafana_loki_client/py.typed
grafana_loki_client/types.py
python_loki_client-0.1.2.dist-info/LICENSE
python_loki_client-0.1.2.dist-info/WHEEL
python_loki_client-0.1.2.dist-info/METADATA
python_loki_client-0.1.2.dist-info/RECORD
