Metadata-Version: 2.1
Name: python-loki-client
Version: 0.1.2
Summary: Python client for Grafana Loki
Home-page: https://github.com/expobrain/python-loki-client
License: MIT
Author: Daniele Esposti
Author-email: daniele.esposti@gmail.com
Requires-Python: >=3.7,<4
Classifier: License :: OSI Approved :: MIT License
Classifier: Programming Language :: Python :: 3
Classifier: Programming Language :: Python :: 3.10
Classifier: Programming Language :: Python :: 3.7
Classifier: Programming Language :: Python :: 3.8
Classifier: Programming Language :: Python :: 3.9
Requires-Dist: attrs (>=20.1.0)
Requires-Dist: httpx (>=0.22.0)
Requires-Dist: python-dateutil (>=2.8.0)
Project-URL: Repository, https://github.com/expobrain/python-loki-client
